elen/__init__.py
elen-0.1.0.dist-info/DESCRIPTION.rst
elen-0.1.0.dist-info/METADATA
elen-0.1.0.dist-info/RECORD
elen-0.1.0.dist-info/WHEEL
elen-0.1.0.dist-info/metadata.json
elen-0.1.0.dist-info/top_level.txt
