Metadata-Version: 2.0
Name: elen
Version: 0.1.0
Summary: Efficient Lexicographic Encoding of Numbers for Python
Home-page: https://github.com/rooterkyberian/elen
Author: Maciej Urbański
Author-email: rooter@kyberian.net
License: MIT license
Keywords: elen
Platform: UNKNOWN
Classifier: Development Status :: 4 - Beta
Classifier: Intended Audience :: Developers
Classifier: Intended Audience :: Science/Research
Classifier: License :: OSI Approved :: MIT License
Classifier: Programming Language :: Python :: 3
Classifier: Programming Language :: Python :: 3.4
Classifier: Programming Language :: Python :: 3.5
Classifier: Programming Language :: Python :: 3.6
